easylenium/__init__.py
easylenium/handler.py
easylenium/location.py
easylenium/login_credentials.py
easylenium/scraper.py
easylenium/utils.py
easylenium-1.0.0.dist-info/AUTHORS
easylenium-1.0.0.dist-info/LICENSE
easylenium-1.0.0.dist-info/METADATA
easylenium-1.0.0.dist-info/WHEEL
easylenium-1.0.0.dist-info/top_level.txt
easylenium-1.0.0.dist-info/RECORD
