Metadata-Version: 2.1
Name: easylenium
Version: 1.0.0
Summary: A powerful web scraping tool for automating data extraction 
Author-email: Hubertus R Mitschke <sturmboe.transit0m@icloud.com>
Project-URL: Homepage, https://github.com/hubertus444/easylenium
Project-URL: Bug Tracker, https://github.com/hubertus444/easylenium/issues
Keywords: web scraping,data extraction,automation,Selenium,web scraping tool,data scraping,web automation,web crawler,data scraping library,Python,website scraping,scraping framework,web data extraction,automated data collection,data scraping tool,data scraping automation,web scraping library
Classifier: Development Status :: 5 - Production/Stable
Classifier: Programming Language :: Python :: 3.7
Classifier: Programming Language :: Python :: 3.8
Classifier: Programming Language :: Python :: 3.9
Classifier: Programming Language :: Python :: 3
Classifier: License :: OSI Approved :: MIT License
Classifier: Operating System :: OS Independent
Requires-Python: >=3.7
License-File: LICENSE
License-File: AUTHORS
